bin2sbom.py
bin2sbom-0.0.8.dist-info/entry_points.txt
bin2sbom-0.0.8.dist-info/LICENSE
bin2sbom-0.0.8.dist-info/WHEEL
bin2sbom-0.0.8.dist-info/METADATA
bin2sbom-0.0.8.dist-info/RECORD
